{"paths":{"0":["fail",0],"1":["BG",0],"2":["dig",0],"3":["BoxOpen",0],"4":["xiaoChuYinXiao",0],"5":["set",0],"6":["螺丝插入音效",0],"7":["点击音效",0],"8":["win",0]},"types":["cc.AudioClip"],"uuids":["0d/0WYRodOgJHo0ncta6z+","2bBzbl2IlGybsYIFRZJwfw","352N1ESexGbpIdjj/J8o5M","69U6YJb6tKqo1uEkWgpgqP","6fzPaRK1pD7pA8OceCK1js","7437aZFEZK06br1FcrqePE","a222wXDaBE+qldq8rFWQq0","d2oFGt8HdB54snSmKsv7ZH","daANV+cytGaZWJiJfqWV8l"],"scenes":{},"redirect":[],"deps":[],"packs":{},"name":"audio","importBase":"import","nativeBase":"native","debug":false,"isZip":false,"encrypted":false,"versions":{"import":[0,"b80e4",1,"ac9fa",2,"039a1",3,"35d58",4,"c672f",5,"5bb97",6,"667ab",7,"af64f",8,"0dff2"],"native":[0,"fde29",1,"8eb7c",2,"742b7",3,"0d7ac",4,"9252b",5,"06d1a",6,"2036b",7,"d2a58",8,"abaee"]}}